[
    {
        "Date": "2022年1月",
        "销售额": 109964.91
    },
    {
        "Date": "2022年2月",
        "销售额": 10848.26
    },
    {
        "Date": "2022年3月",
        "销售额": 123601.86
    },
    {
        "Date": "2022年4月",
        "销售额": 180925.1
    },
    {
        "Date": "2022年5月",
        "销售额": 172546.54
    },
    {
        "Date": "2022年6月",
        "销售额": 244952.15
    },
    {
        "Date": "2022年7月",
        "销售额": 273461.3
    },
    {
        "Date": "2022年8月",
        "销售额": 60019.3
    }
]